alpaca/__init__.py
alpaca/__init__.pyi
alpaca/biblio/__init__.py
alpaca/biblio/__init__.pyi
alpaca/biblio/biblio.py
alpaca/chiPT/__init__.py
alpaca/chiPT/chiral.py
alpaca/chiPT/ffunction.pickle
alpaca/chiPT/ffunction_Aloni.csv
alpaca/chiPT/makeffunction.py
alpaca/chiPT/mathematica/2omega.m
alpaca/chiPT/mathematica/2omega.py
alpaca/chiPT/mathematica/3pi0_a0.m
alpaca/chiPT/mathematica/3pi0_a0.py
alpaca/chiPT/mathematica/3pi0_chPT.m
alpaca/chiPT/mathematica/3pi0_chPT.py
alpaca/chiPT/mathematica/3pi0_f0.m
alpaca/chiPT/mathematica/3pi0_f0.py
alpaca/chiPT/mathematica/3pi0_f2.m
alpaca/chiPT/mathematica/3pi0_f2.py
alpaca/chiPT/mathematica/3pi0_sigma.m
alpaca/chiPT/mathematica/3pi0_sigma.py
alpaca/chiPT/mathematica/eta2pi0_a0.m
alpaca/chiPT/mathematica/eta2pi0_a0.py
alpaca/chiPT/mathematica/eta2pi0_chPT.m
alpaca/chiPT/mathematica/eta2pi0_chPT.py
alpaca/chiPT/mathematica/eta2pi0_f0.m
alpaca/chiPT/mathematica/eta2pi0_f0.py
alpaca/chiPT/mathematica/eta2pi0_f2.m
alpaca/chiPT/mathematica/eta2pi0_f2.py
alpaca/chiPT/mathematica/eta2pi0_sigma.m
alpaca/chiPT/mathematica/eta2pi0_sigma.py
alpaca/chiPT/mathematica/etapipi_a0.m
alpaca/chiPT/mathematica/etapipi_a0.py
alpaca/chiPT/mathematica/etapipi_chPT.m
alpaca/chiPT/mathematica/etapipi_chPT.py
alpaca/chiPT/mathematica/etapipi_f0.m
alpaca/chiPT/mathematica/etapipi_f0.py
alpaca/chiPT/mathematica/etapipi_f2.m
alpaca/chiPT/mathematica/etapipi_f2.py
alpaca/chiPT/mathematica/etapipi_sigma.m
alpaca/chiPT/mathematica/etapipi_sigma.py
alpaca/chiPT/mathematica/etapr2pi0_a0.m
alpaca/chiPT/mathematica/etapr2pi0_a0.py
alpaca/chiPT/mathematica/etapr2pi0_chPT.m
alpaca/chiPT/mathematica/etapr2pi0_chPT.py
alpaca/chiPT/mathematica/etapr2pi0_f0.m
alpaca/chiPT/mathematica/etapr2pi0_f0.py
alpaca/chiPT/mathematica/etapr2pi0_f2.m
alpaca/chiPT/mathematica/etapr2pi0_f2.py
alpaca/chiPT/mathematica/etapr2pi0_sigma.m
alpaca/chiPT/mathematica/etapr2pi0_sigma.py
alpaca/chiPT/mathematica/etaprpipi_a0.m
alpaca/chiPT/mathematica/etaprpipi_a0.py
alpaca_alps-1.0.0.dist-info/LICENSE
alpaca_alps-1.0.0.dist-info/METADATA
alpaca_alps-1.0.0.dist-info/WHEEL
alpaca_alps-1.0.0.dist-info/RECORD
