Metadata-Version: 2.3
Name: alpaca-ALPs
Version: 1.0.0
Summary: The ALP Automatic Computing Algorithm
License: MIT
Author: Jorge Alda
Author-email: jorge.alda@pd.infn.it
Requires-Python: >=3.10,<3.14
Classifier: Development Status :: 4 - Beta
Classifier: Intended Audience :: Science/Research
Classifier: License :: OSI Approved :: MIT License
Classifier: Programming Language :: Python :: 3.10
Classifier: Programming Language :: Python :: 3.11
Classifier: Programming Language :: Python :: 3.12
Classifier: Topic :: Scientific/Engineering :: Physics
Requires-Dist: distinctipy (>=1.3.4,<2.0.0)
Requires-Dist: flavio (>=2.6.1,<3.0.0)
Requires-Dist: lazy-loader (>=0.4,<0.5)
Requires-Dist: requests (>=2.32.3,<3.0.0)
Requires-Dist: sympy (==1.13.3)
Requires-Dist: vegas (>=6.1.1,<7.0.0)
Project-URL: Documentation, https://alpaca-alps.readthedocs.io/latest/
Project-URL: DOI, https://doi.org/10.5281/zenodo.16447036
Project-URL: Examples, https://github.com/alp-aca/examples
Project-URL: Manual, https://arxiv.org/abs/2508.08354
Project-URL: Repository, https://github.com/alp-aca/alp-aca
